{
    "root": "/work/CVAE",
    "program": "cvae.py",
    "startedAt": "2020-06-28T07:17:40.345286",
    "host": "1a7d5c5f89ef",
    "username": "root",
    "executable": "/opt/conda/envs/face/bin/python",
    "os": "Linux-4.15.0-55-generic-x86_64-with-debian-stretch-sid",
    "python": "3.6.10",
    "gpu": "Tesla V100-SXM2-32GB",
    "gpu_count": 8,
    "cpu_count": 80,
    "cuda": "10.1.243",
    "args": [],
    "state": "failed",
    "jobType": "train",
    "mode": "run",
    "project": "CVAE",
    "heartbeatAt": "2020-06-28T07:18:09.817821",
    "exitcode": 1
}
